jsonlogic_rs/__init__.py
jsonlogic_rs/jsonlogic.cpython-310-x86_64-linux-gnu.so
jsonlogic_rs-0.5.0.dist-info/top_level.txt
jsonlogic_rs-0.5.0.dist-info/RECORD
jsonlogic_rs-0.5.0.dist-info/LICENSE
jsonlogic_rs-0.5.0.dist-info/METADATA
jsonlogic_rs-0.5.0.dist-info/WHEEL
