Metadata-Version: 2.1
Name: jsonlogic-rs
Version: 0.5.0
Summary: JsonLogic implemented with a Rust backend
Home-page: https://www.github.com/bestowinc/json-logic-rs
Author: Matthew Planchard
Author-email: msplanchard@gmail.com
Maintainer-email: msplanchard@gmail.com
Keywords: json,jsonlogic,s-expressions,rust
Classifier: Development Status :: 5 - Production/Stable
Classifier: Intended Audience :: Developers
Classifier: License :: OSI Approved :: MIT License
Classifier: Natural Language :: English
Classifier: Operating System :: POSIX :: Linux
Classifier: Operating System :: MacOS :: MacOS X
Classifier: Operating System :: Microsoft :: Windows
Classifier: Programming Language :: Python
Classifier: Programming Language :: Python :: 3 :: Only
Classifier: Programming Language :: Python :: 3.7
Classifier: Programming Language :: Python :: 3.8
Classifier: Programming Language :: Python :: 3.9
Classifier: Programming Language :: Python :: 3.10
Classifier: Programming Language :: Python :: 3.11
Classifier: Programming Language :: Python :: 3.12
Classifier: Programming Language :: Rust
License-File: LICENSE
